pydistill/__init__.py
pydistill/cli.py
pydistill/config.py
pydistill/discovery.py
pydistill/extractor.py
pydistill/models.py
pydistill/py.typed
pydistill/rewriter.py
pydistill-0.1.0.dist-info/METADATA
pydistill-0.1.0.dist-info/WHEEL
pydistill-0.1.0.dist-info/entry_points.txt
pydistill-0.1.0.dist-info/RECORD
