Metadata-Version: 2.4
Name: pydistill
Version: 0.1.0
Summary: Extract Python models and dependencies into standalone packages
Project-URL: Homepage, https://github.com/elmcrest/pydistill
Project-URL: Repository, https://github.com/elmcrest/pydistill.git
Project-URL: Issues, https://github.com/elmcrest/pydistill/issues
Author-email: Marius Räsener <marius@raesener.de>
License: MIT
Keywords: ast,dependencies,extraction,models,pydantic,refactoring
Classifier: Development Status :: 3 - Alpha
Classifier: Intended Audience :: Developers
Classifier: License :: OSI Approved :: MIT License
Classifier: Programming Language :: Python :: 3
Classifier: Programming Language :: Python :: 3.11
Classifier: Programming Language :: Python :: 3.12
Classifier: Programming Language :: Python :: 3.13
Classifier: Topic :: Software Development :: Code Generators
Classifier: Typing :: Typed
Requires-Python: >=3.11
Requires-Dist: pydantic[email]>=2.12.5
